LICENSE
README.md
setup.py
selenium_pro/__init__.py
selenium_pro.egg-info/PKG-INFO
selenium_pro.egg-info/SOURCES.txt
selenium_pro.egg-info/dependency_links.txt
selenium_pro.egg-info/requires.txt
selenium_pro.egg-info/top_level.txt
selenium_pro/common/__init__.py
selenium_pro/common/exceptions.py
selenium_pro/webdriver/__init__.py
selenium_pro/webdriver/android/__init__.py
selenium_pro/webdriver/android/webdriver.py
selenium_pro/webdriver/blackberry/__init__.py
selenium_pro/webdriver/blackberry/webdriver.py
selenium_pro/webdriver/chrome/__init__.py
selenium_pro/webdriver/chrome/options.py
selenium_pro/webdriver/chrome/remote_connection.py
selenium_pro/webdriver/chrome/service.py
selenium_pro/webdriver/chrome/webdriver.py
selenium_pro/webdriver/common/__init__.py
selenium_pro/webdriver/common/action_chains.py
selenium_pro/webdriver/common/alert.py
selenium_pro/webdriver/common/by.py
selenium_pro/webdriver/common/desired_capabilities.py
selenium_pro/webdriver/common/keys.py
selenium_pro/webdriver/common/proxy.py
selenium_pro/webdriver/common/service.py
selenium_pro/webdriver/common/touch_actions.py
selenium_pro/webdriver/common/utils.py
selenium_pro/webdriver/common/actions/__init__.py
selenium_pro/webdriver/common/actions/action_builder.py
selenium_pro/webdriver/common/actions/input_device.py
selenium_pro/webdriver/common/actions/interaction.py
selenium_pro/webdriver/common/actions/key_actions.py
selenium_pro/webdriver/common/actions/key_input.py
selenium_pro/webdriver/common/actions/mouse_button.py
selenium_pro/webdriver/common/actions/pointer_actions.py
selenium_pro/webdriver/common/actions/pointer_input.py
selenium_pro/webdriver/common/html5/__init__.py
selenium_pro/webdriver/common/html5/application_cache.py
selenium_pro/webdriver/edge/__init__.py
selenium_pro/webdriver/edge/options.py
selenium_pro/webdriver/edge/service.py
selenium_pro/webdriver/edge/webdriver.py
selenium_pro/webdriver/firefox/__init__.py
selenium_pro/webdriver/firefox/extension_connection.py
selenium_pro/webdriver/firefox/firefox_binary.py
selenium_pro/webdriver/firefox/firefox_profile.py
selenium_pro/webdriver/firefox/options.py
