Metadata-Version: 2.1
Name: selenium-pro
Version: 1.4.4
Summary: Automation Library
Home-page: UNKNOWN
Author: DataKund
Author-email: datakund@gmail.com
License: Apache License 2.0
Keywords: selenium no-html web-scraping bots test-automation no-code low-code cloud proxy datakund
Platform: UNKNOWN
